[
    {
        "date": "01-22-2022",
        "court": "Wiley",
        "food": "Scrambled Eggs",
        "meal_time": "Breakfast",
        "ratings": 2.8,
        "picture": "",
        "ratings_count": 46
    },
    {
        "date": "01-22-2022",
        "court": "Wiley",
        "food": "Homestyle Sausage Gravy",
        "meal_time": "Breakfast",
        "ratings": 4.4,
        "picture": "",
        "ratings_count": 22
    },
    {
        "date": "01-22-2022",
        "court": "Wiley",
        "food": "Biscuits",
        "meal_time": "Breakfast",
        "ratings": 2.9,
        "picture": "",
        "ratings_count": 5
    },
    {
        "date": "01-22-2022",
        "court": "Wiley",
        "food": "Oatmeal",
        "meal_time": "Breakfast",
        "ratings": 3.4,
        "picture": "",
        "ratings_count": 61
    },
    {
        "date": "01-22-2022",
        "court": "Wiley",
        "food": "Sausage Links",
        "meal_time": "Breakfast",
        "ratings": 3.4,
        "picture": "",
        "ratings_count": 86
    },
    {
        "date": "01-22-2022",
        "court": "Wiley",
        "food": "Hash Brown",
        "meal_time": "Breakfast",
        "ratings": 4.0,
        "picture": "",
        "ratings_count": 66
    },
    {
        "date": "01-22-2022",
        "court": "Wiley",
        "food": "Pineapple Chunks",
        "meal_time": "Breakfast",
        "ratings": 1.7,
        "picture": "",
        "ratings_count": 68
    },
    {
        "date": "01-22-2022",
        "court": "Wiley",
        "food": "Assorted Donuts",
        "meal_time": "Breakfast",
        "ratings": 1.6,
        "picture": "",
        "ratings_count": 62
    },
    {
        "date": "01-22-2022",
        "court": "Wiley",
        "food": "Cinnamon Muffin",
        "meal_time": "Breakfast",
        "ratings": 2.8,
        "picture": "",
        "ratings_count": 65
    },
    {
        "date": "01-22-2022",
        "court": "Wiley",
        "food": "Creamy Sunflower Butter Spread",
        "meal_time": "Breakfast",
        "ratings": 2.9,
        "picture": "",
        "ratings_count": 46
    },
    {
        "date": "01-22-2022",
        "court": "Wiley",
        "food": "Margarine Cup",
        "meal_time": "Breakfast",
        "ratings": 1.4,
        "picture": "",
        "ratings_count": 39
    },
    {
        "date": "01-22-2022",
        "court": "Wiley",
        "food": "GF White Bread",
        "meal_time": "Breakfast",
        "ratings": 1.7,
        "picture": "",
        "ratings_count": 64
    },
    {
        "date": "01-22-2022",
        "court": "Wiley",
        "food": "GF Plain Bagel",
        "meal_time": "Breakfast",
        "ratings": 3.0,
        "picture": "",
        "ratings_count": 98
    },
    {
        "date": "01-22-2022",
        "court": "Wiley",
        "food": "GF Blueberry Muffin",
        "meal_time": "Breakfast",
        "ratings": 1.6,
        "picture": "",
        "ratings_count": 68
    },
    {
        "date": "01-22-2022",
        "court": "Wiley",
        "food": "Hamburger",
        "meal_time": "Lunch",
        "ratings": 3.3,
        "picture": "",
        "ratings_count": 6
    },
    {
        "date": "01-22-2022",
        "court": "Wiley",
        "food": "Crinkle Cut Fries",
        "meal_time": "Lunch",
        "ratings": 3.6,
        "picture": "",
        "ratings_count": 98
    },
    {
        "date": "01-22-2022",
        "court": "Wiley",
        "food": "Greek Pollock Mozzarella",
        "meal_time": "Lunch",
        "ratings": 1.7,
        "picture": "",
        "ratings_count": 16
    },
    {
        "date": "01-22-2022",
        "court": "Wiley",
        "food": "Wild Rice",
        "meal_time": "Lunch",
        "ratings": 3.6,
        "picture": "",
        "ratings_count": 86
    },
    {
        "date": "01-22-2022",
        "court": "Wiley",
        "food": "Roasted Green Beans",
        "meal_time": "Lunch",
        "ratings": 2.7,
        "picture": "",
        "ratings_count": 57
    },
    {
        "date": "01-22-2022",
        "court": "Wiley",
        "food": "Cheez Stix",
        "meal_time": "Lunch",
        "ratings": 3.6,
        "picture": "",
        "ratings_count": 72
    },
    {
        "date": "01-22-2022",
        "court": "Wiley",
        "food": "Marinara Sauce",
        "meal_time": "Lunch",
        "ratings": 3.8,
        "picture": "",
        "ratings_count": 99
    },
    {
        "date": "01-22-2022",
        "court": "Wiley",
        "food": "Salad Bar ",
        "meal_time": "Lunch",
        "ratings": 2.9,
        "picture": "",
        "ratings_count": 94
    },
    {
        "date": "01-22-2022",
        "court": "Wiley",
        "food": "Pineapple Chunks",
        "meal_time": "Lunch",
        "ratings": 1.1,
        "picture": "",
        "ratings_count": 99
    },
    {
        "date": "01-22-2022",
        "court": "Wiley",
        "food": "Candied Pork Chop",
        "meal_time": "Lunch",
        "ratings": 1.1,
        "picture": "",
        "ratings_count": 83
    },
    {
        "date": "01-22-2022",
        "court": "Wiley",
        "food": "Jasmine Rice",
        "meal_time": "Lunch",
        "ratings": 3.7,
        "picture": "",
        "ratings_count": 34
    },
    {
        "date": "01-22-2022",
        "court": "Wiley",
        "food": "Roasted Green Beans",
        "meal_time": "Lunch",
        "ratings": 4.5,
        "picture": "",
        "ratings_count": 64
    },
    {
        "date": "01-22-2022",
        "court": "Wiley",
        "food": "Pineapple Chunks",
        "meal_time": "Lunch",
        "ratings": 3.0,
        "picture": "",
        "ratings_count": 15
    },
    {
        "date": "01-22-2022",
        "court": "Wiley",
        "food": "GF Mint Chocolate Chip Cookie",
        "meal_time": "Lunch",
        "ratings": 3.4,
        "picture": "",
        "ratings_count": 31
    },
    {
        "date": "01-22-2022",
        "court": "Wiley",
        "food": "Peanut Butter Cookie",
        "meal_time": "Lunch",
        "ratings": 4.4,
        "picture": "",
        "ratings_count": 23
    },
    {
        "date": "01-22-2022",
        "court": "Wiley",
        "food": "Chocolate Pudding",
        "meal_time": "Lunch",
        "ratings": 1.8,
        "picture": "",
        "ratings_count": 97
    },
    {
        "date": "01-22-2022",
        "court": "Wiley",
        "food": "Pound Cake",
        "meal_time": "Lunch",
        "ratings": 3.4,
        "picture": "",
        "ratings_count": 83
    },
    {
        "date": "01-22-2022",
        "court": "Wiley",
        "food": "Sliced Strawberries",
        "meal_time": "Lunch",
        "ratings": 3.6,
        "picture": "",
        "ratings_count": 22
    },
    {
        "date": "01-22-2022",
        "court": "Wiley",
        "food": "Jumbo Cheese Ravioli",
        "meal_time": "Lunch",
        "ratings": 1.5,
        "picture": "",
        "ratings_count": 25
    },
    {
        "date": "01-22-2022",
        "court": "Wiley",
        "food": "Meatless Spaghetti Sauce",
        "meal_time": "Lunch",
        "ratings": 4.8,
        "picture": "",
        "ratings_count": 15
    },
    {
        "date": "01-22-2022",
        "court": "Wiley",
        "food": "Garlic Bread",
        "meal_time": "Lunch",
        "ratings": 2.0,
        "picture": "",
        "ratings_count": 41
    },
    {
        "date": "01-22-2022",
        "court": "Wiley",
        "food": "Chicken Noodle Soup",
        "meal_time": "Lunch",
        "ratings": 4.1,
        "picture": "",
        "ratings_count": 63
    },
    {
        "date": "01-22-2022",
        "court": "Wiley",
        "food": "GF Hamburger Bun",
        "meal_time": "Lunch",
        "ratings": 1.6,
        "picture": "",
        "ratings_count": 97
    },
    {
        "date": "01-22-2022",
        "court": "Wiley",
        "food": "Malibu Burger",
        "meal_time": "Lunch",
        "ratings": 4.0,
        "picture": "",
        "ratings_count": 6
    },
    {
        "date": "01-22-2022",
        "court": "Wiley",
        "food": "GF Hot Dog Bun",
        "meal_time": "Lunch",
        "ratings": 2.5,
        "picture": "",
        "ratings_count": 9
    },
    {
        "date": "01-22-2022",
        "court": "Wiley",
        "food": "Mozz Style Shredded Vegan Cheese",
        "meal_time": "Lunch",
        "ratings": 3.1,
        "picture": "",
        "ratings_count": 10
    },
    {
        "date": "01-22-2022",
        "court": "Wiley",
        "food": "Margarine Cup",
        "meal_time": "Lunch",
        "ratings": 2.7,
        "picture": "",
        "ratings_count": 27
    },
    {
        "date": "01-22-2022",
        "court": "Wiley",
        "food": "Creamy Sunflower Butter Spread",
        "meal_time": "Lunch",
        "ratings": 3.1,
        "picture": "",
        "ratings_count": 99
    },
    {
        "date": "01-22-2022",
        "court": "Wiley",
        "food": "GF White Bread",
        "meal_time": "Lunch",
        "ratings": 4.1,
        "picture": "",
        "ratings_count": 71
    },
    {
        "date": "01-22-2022",
        "court": "Wiley",
        "food": "Italian Ice",
        "meal_time": "Lunch",
        "ratings": 5.0,
        "picture": "",
        "ratings_count": 26
    },
    {
        "date": "01-22-2022",
        "court": "Wiley",
        "food": "GF Cookies",
        "meal_time": "Lunch",
        "ratings": 3.0,
        "picture": "",
        "ratings_count": 54
    },
    {
        "date": "01-22-2022",
        "court": "Wiley",
        "food": "Breaded Pork Tenderloin",
        "meal_time": "Dinner",
        "ratings": 2.6,
        "picture": "",
        "ratings_count": 63
    },
    {
        "date": "01-22-2022",
        "court": "Wiley",
        "food": "Grilled Bell Pepper",
        "meal_time": "Dinner",
        "ratings": 1.1,
        "picture": "",
        "ratings_count": 2
    },
    {
        "date": "01-22-2022",
        "court": "Wiley",
        "food": "Crinkle Cut Fries",
        "meal_time": "Dinner",
        "ratings": 1.8,
        "picture": "",
        "ratings_count": 74
    },
    {
        "date": "01-22-2022",
        "court": "Wiley",
        "food": "Rotini",
        "meal_time": "Dinner",
        "ratings": 3.0,
        "picture": "",
        "ratings_count": 76
    },
    {
        "date": "01-22-2022",
        "court": "Wiley",
        "food": "Marinara Sauce",
        "meal_time": "Dinner",
        "ratings": 2.1,
        "picture": "",
        "ratings_count": 19
    },
    {
        "date": "01-22-2022",
        "court": "Wiley",
        "food": "GF Alfredo Sauce",
        "meal_time": "Dinner",
        "ratings": 3.3,
        "picture": "",
        "ratings_count": 75
    },
    {
        "date": "01-22-2022",
        "court": "Wiley",
        "food": "Grated Parmesan Cheese",
        "meal_time": "Dinner",
        "ratings": 1.1,
        "picture": "",
        "ratings_count": 66
    },
    {
        "date": "01-22-2022",
        "court": "Wiley",
        "food": "Ancho Chili Bone In Chicken Breast ",
        "meal_time": "Dinner",
        "ratings": 2.6,
        "picture": "",
        "ratings_count": 15
    },
    {
        "date": "01-22-2022",
        "court": "Wiley",
        "food": "Green Beans",
        "meal_time": "Dinner",
        "ratings": 1.7,
        "picture": "",
        "ratings_count": 33
    },
    {
        "date": "01-22-2022",
        "court": "Wiley",
        "food": "Tri Color Quinoa",
        "meal_time": "Dinner",
        "ratings": 1.2,
        "picture": "",
        "ratings_count": 77
    },
    {
        "date": "01-22-2022",
        "court": "Wiley",
        "food": "Cheez Stix",
        "meal_time": "Dinner",
        "ratings": 2.4,
        "picture": "",
        "ratings_count": 99
    },
    {
        "date": "01-22-2022",
        "court": "Wiley",
        "food": "Marinara Sauce",
        "meal_time": "Dinner",
        "ratings": 2.0,
        "picture": "",
        "ratings_count": 56
    },
    {
        "date": "01-22-2022",
        "court": "Wiley",
        "food": "Salad Bar ",
        "meal_time": "Dinner",
        "ratings": 1.0,
        "picture": "",
        "ratings_count": 23
    },
    {
        "date": "01-22-2022",
        "court": "Wiley",
        "food": "Pineapple Chunks",
        "meal_time": "Dinner",
        "ratings": 2.6,
        "picture": "",
        "ratings_count": 84
    },
    {
        "date": "01-22-2022",
        "court": "Wiley",
        "food": "GF Macaroni and Cheese",
        "meal_time": "Dinner",
        "ratings": 3.7,
        "picture": "",
        "ratings_count": 62
    },
    {
        "date": "01-22-2022",
        "court": "Wiley",
        "food": "Green Beans",
        "meal_time": "Dinner",
        "ratings": 4.2,
        "picture": "",
        "ratings_count": 22
    },
    {
        "date": "01-22-2022",
        "court": "Wiley",
        "food": "Austin Blues Pulled Pork",
        "meal_time": "Dinner",
        "ratings": 3.4,
        "picture": "",
        "ratings_count": 41
    },
    {
        "date": "01-22-2022",
        "court": "Wiley",
        "food": "Ken's Cannonball BBQ Sauce",
        "meal_time": "Dinner",
        "ratings": 1.4,
        "picture": "",
        "ratings_count": 37
    },
    {
        "date": "01-22-2022",
        "court": "Wiley",
        "food": "Pineapple Chunks",
        "meal_time": "Dinner",
        "ratings": 3.0,
        "picture": "",
        "ratings_count": 40
    },
    {
        "date": "01-22-2022",
        "court": "Wiley",
        "food": "GF Mint Chocolate Chip Cookie",
        "meal_time": "Dinner",
        "ratings": 1.3,
        "picture": "",
        "ratings_count": 29
    },
    {
        "date": "01-22-2022",
        "court": "Wiley",
        "food": "Peanut Butter Cookie",
        "meal_time": "Dinner",
        "ratings": 1.9,
        "picture": "",
        "ratings_count": 74
    },
    {
        "date": "01-22-2022",
        "court": "Wiley",
        "food": "Chocolate Pudding",
        "meal_time": "Dinner",
        "ratings": 3.5,
        "picture": "",
        "ratings_count": 64
    },
    {
        "date": "01-22-2022",
        "court": "Wiley",
        "food": "Pound Cake",
        "meal_time": "Dinner",
        "ratings": 4.0,
        "picture": "",
        "ratings_count": 99
    },
    {
        "date": "01-22-2022",
        "court": "Wiley",
        "food": "Sliced Strawberries",
        "meal_time": "Dinner",
        "ratings": 3.5,
        "picture": "",
        "ratings_count": 69
    },
    {
        "date": "01-22-2022",
        "court": "Wiley",
        "food": "Bean and Cheese Burrito",
        "meal_time": "Dinner",
        "ratings": 1.7,
        "picture": "",
        "ratings_count": 76
    },
    {
        "date": "01-22-2022",
        "court": "Wiley",
        "food": "Mild Picante Sauce",
        "meal_time": "Dinner",
        "ratings": 1.2,
        "picture": "",
        "ratings_count": 51
    },
    {
        "date": "01-22-2022",
        "court": "Wiley",
        "food": "Sour Cream",
        "meal_time": "Dinner",
        "ratings": 2.3,
        "picture": "",
        "ratings_count": 4
    },
    {
        "date": "01-22-2022",
        "court": "Wiley",
        "food": "Chicken Noodle Soup",
        "meal_time": "Dinner",
        "ratings": 2.8,
        "picture": "",
        "ratings_count": 2
    },
    {
        "date": "01-22-2022",
        "court": "Wiley",
        "food": "GF Hamburger Bun",
        "meal_time": "Dinner",
        "ratings": 1.1,
        "picture": "",
        "ratings_count": 74
    },
    {
        "date": "01-22-2022",
        "court": "Wiley",
        "food": "Malibu Burger",
        "meal_time": "Dinner",
        "ratings": 2.4,
        "picture": "",
        "ratings_count": 75
    },
    {
        "date": "01-22-2022",
        "court": "Wiley",
        "food": "GF Hot Dog Bun",
        "meal_time": "Dinner",
        "ratings": 4.8,
        "picture": "",
        "ratings_count": 42
    },
    {
        "date": "01-22-2022",
        "court": "Wiley",
        "food": "Mozz Style Shredded Vegan Cheese",
        "meal_time": "Dinner",
        "ratings": 3.8,
        "picture": "",
        "ratings_count": 89
    },
    {
        "date": "01-22-2022",
        "court": "Wiley",
        "food": "Margarine Cup",
        "meal_time": "Dinner",
        "ratings": 1.4,
        "picture": "",
        "ratings_count": 87
    },
    {
        "date": "01-22-2022",
        "court": "Wiley",
        "food": "Creamy Sunflower Butter Spread",
        "meal_time": "Dinner",
        "ratings": 3.9,
        "picture": "",
        "ratings_count": 83
    },
    {
        "date": "01-22-2022",
        "court": "Wiley",
        "food": "GF White Bread",
        "meal_time": "Dinner",
        "ratings": 1.0,
        "picture": "",
        "ratings_count": 55
    },
    {
        "date": "01-22-2022",
        "court": "Wiley",
        "food": "GF Cookies",
        "meal_time": "Dinner",
        "ratings": 1.6,
        "picture": "",
        "ratings_count": 37
    },
    {
        "date": "01-22-2022",
        "court": "Wiley",
        "food": "Italian Ice",
        "meal_time": "Dinner",
        "ratings": 1.7,
        "picture": "",
        "ratings_count": 65
    },
    {
        "date": "01-22-2022",
        "court": "Ford",
        "food": "BoilerQ Barbeque Sauces",
        "meal_time": "Lunch",
        "ratings": 2.6,
        "picture": "",
        "ratings_count": 50
    },
    {
        "date": "01-22-2022",
        "court": "Ford",
        "food": "Hamburgers",
        "meal_time": "Lunch",
        "ratings": 2.1,
        "picture": "",
        "ratings_count": 93
    },
    {
        "date": "01-22-2022",
        "court": "Ford",
        "food": "Roasted BBQ Chicken Thighs",
        "meal_time": "Lunch",
        "ratings": 3.7,
        "picture": "",
        "ratings_count": 17
    },
    {
        "date": "01-22-2022",
        "court": "Ford",
        "food": "Thin Cut Fries",
        "meal_time": "Lunch",
        "ratings": 2.9,
        "picture": "",
        "ratings_count": 2
    },
    {
        "date": "01-22-2022",
        "court": "Ford",
        "food": "Popcorn Shrimp",
        "meal_time": "Lunch",
        "ratings": 4.4,
        "picture": "",
        "ratings_count": 11
    },
    {
        "date": "01-22-2022",
        "court": "Ford",
        "food": "Zesty Cocktail Sauce",
        "meal_time": "Lunch",
        "ratings": 3.9,
        "picture": "",
        "ratings_count": 60
    },
    {
        "date": "01-22-2022",
        "court": "Ford",
        "food": "Edamame",
        "meal_time": "Lunch",
        "ratings": 3.6,
        "picture": "",
        "ratings_count": 13
    },
    {
        "date": "01-22-2022",
        "court": "Ford",
        "food": "Vegan Jambalaya",
        "meal_time": "Lunch",
        "ratings": 1.0,
        "picture": "",
        "ratings_count": 11
    },
    {
        "date": "01-22-2022",
        "court": "Ford",
        "food": "Hush Puppies",
        "meal_time": "Lunch",
        "ratings": 3.5,
        "picture": "",
        "ratings_count": 51
    },
    {
        "date": "01-22-2022",
        "court": "Ford",
        "food": "Mustard Greens with Bacon",
        "meal_time": "Lunch",
        "ratings": 3.2,
        "picture": "",
        "ratings_count": 36
    },
    {
        "date": "01-22-2022",
        "court": "Ford",
        "food": "Chicken Pesto Pizza",
        "meal_time": "Lunch",
        "ratings": 3.2,
        "picture": "",
        "ratings_count": 93
    },
    {
        "date": "01-22-2022",
        "court": "Ford",
        "food": "Cheese Pizza",
        "meal_time": "Lunch",
        "ratings": 3.5,
        "picture": "",
        "ratings_count": 39
    },
    {
        "date": "01-22-2022",
        "court": "Ford",
        "food": "Sundae Bar",
        "meal_time": "Lunch",
        "ratings": 4.8,
        "picture": "",
        "ratings_count": 21
    },
    {
        "date": "01-22-2022",
        "court": "Ford",
        "food": "Homemade Chocolate Chip Cookie",
        "meal_time": "Lunch",
        "ratings": 4.7,
        "picture": "",
        "ratings_count": 66
    },
    {
        "date": "01-22-2022",
        "court": "Ford",
        "food": "Apple Nut Cake",
        "meal_time": "Lunch",
        "ratings": 2.3,
        "picture": "",
        "ratings_count": 94
    },
    {
        "date": "01-22-2022",
        "court": "Ford",
        "food": "Lemon Meringue Pie",
        "meal_time": "Lunch",
        "ratings": 1.1,
        "picture": "",
        "ratings_count": 28
    },
    {
        "date": "01-22-2022",
        "court": "Ford",
        "food": "Edamame",
        "meal_time": "Lunch",
        "ratings": 4.5,
        "picture": "",
        "ratings_count": 89
    },
    {
        "date": "01-22-2022",
        "court": "Ford",
        "food": "Vegan Jambalaya",
        "meal_time": "Lunch",
        "ratings": 2.9,
        "picture": "",
        "ratings_count": 64
    },
    {
        "date": "01-22-2022",
        "court": "Ford",
        "food": "Whole Green Beans",
        "meal_time": "Lunch",
        "ratings": 1.9,
        "picture": "",
        "ratings_count": 73
    },
    {
        "date": "01-22-2022",
        "court": "Ford",
        "food": "Salad Bar ",
        "meal_time": "Lunch",
        "ratings": 1.9,
        "picture": "",
        "ratings_count": 56
    },
    {
        "date": "01-22-2022",
        "court": "Ford",
        "food": "Vanilla Yogurt",
        "meal_time": "Lunch",
        "ratings": 4.9,
        "picture": "",
        "ratings_count": 2
    },
    {
        "date": "01-22-2022",
        "court": "Ford",
        "food": "Strawberry Yogurt",
        "meal_time": "Lunch",
        "ratings": 2.1,
        "picture": "",
        "ratings_count": 56
    },
    {
        "date": "01-22-2022",
        "court": "Ford",
        "food": "Grapefruit Wedges",
        "meal_time": "Lunch",
        "ratings": 2.0,
        "picture": "",
        "ratings_count": 83
    },
    {
        "date": "01-22-2022",
        "court": "Ford",
        "food": "Mango Chunks",
        "meal_time": "Lunch",
        "ratings": 2.0,
        "picture": "",
        "ratings_count": 14
    },
    {
        "date": "01-22-2022",
        "court": "Ford",
        "food": "Malibu Burger",
        "meal_time": "Lunch",
        "ratings": 3.7,
        "picture": "",
        "ratings_count": 15
    },
    {
        "date": "01-22-2022",
        "court": "Ford",
        "food": "GF White Bread",
        "meal_time": "Lunch",
        "ratings": 2.3,
        "picture": "",
        "ratings_count": 46
    },
    {
        "date": "01-22-2022",
        "court": "Ford",
        "food": "GF Hot Dog Bun",
        "meal_time": "Lunch",
        "ratings": 3.9,
        "picture": "",
        "ratings_count": 3
    },
    {
        "date": "01-22-2022",
        "court": "Ford",
        "food": "GF Hamburger Bun",
        "meal_time": "Lunch",
        "ratings": 3.1,
        "picture": "",
        "ratings_count": 75
    },
    {
        "date": "01-22-2022",
        "court": "Ford",
        "food": "Dark Chocolate Sunflower Butter",
        "meal_time": "Lunch",
        "ratings": 2.1,
        "picture": "",
        "ratings_count": 25
    },
    {
        "date": "01-22-2022",
        "court": "Ford",
        "food": "Smart Balance Margarine",
        "meal_time": "Lunch",
        "ratings": 2.5,
        "picture": "",
        "ratings_count": 7
    },
    {
        "date": "01-22-2022",
        "court": "Ford",
        "food": "Mozz Style Shredded Vegan Cheese",
        "meal_time": "Lunch",
        "ratings": 2.5,
        "picture": "",
        "ratings_count": 52
    },
    {
        "date": "01-22-2022",
        "court": "Ford",
        "food": "GF Pizza Crust",
        "meal_time": "Lunch",
        "ratings": 4.7,
        "picture": "",
        "ratings_count": 59
    },
    {
        "date": "01-22-2022",
        "court": "Ford",
        "food": "Italian Ice",
        "meal_time": "Lunch",
        "ratings": 2.3,
        "picture": "",
        "ratings_count": 32
    },
    {
        "date": "01-22-2022",
        "court": "Ford",
        "food": "BoilerQ Barbeque Sauces",
        "meal_time": "Dinner",
        "ratings": 4.4,
        "picture": "",
        "ratings_count": 69
    },
    {
        "date": "01-22-2022",
        "court": "Ford",
        "food": "Hamburgers",
        "meal_time": "Dinner",
        "ratings": 1.3,
        "picture": "",
        "ratings_count": 18
    },
    {
        "date": "01-22-2022",
        "court": "Ford",
        "food": "Thin Cut Fries",
        "meal_time": "Dinner",
        "ratings": 3.8,
        "picture": "",
        "ratings_count": 63
    },
    {
        "date": "01-22-2022",
        "court": "Ford",
        "food": "Chicken Pie",
        "meal_time": "Dinner",
        "ratings": 4.5,
        "picture": "",
        "ratings_count": 75
    },
    {
        "date": "01-22-2022",
        "court": "Ford",
        "food": "Chickpeas and Mushroom Ragout",
        "meal_time": "Dinner",
        "ratings": 3.0,
        "picture": "",
        "ratings_count": 44
    },
    {
        "date": "01-22-2022",
        "court": "Ford",
        "food": "Whipped Potatoes",
        "meal_time": "Dinner",
        "ratings": 3.0,
        "picture": "",
        "ratings_count": 68
    },
    {
        "date": "01-22-2022",
        "court": "Ford",
        "food": "Linguini",
        "meal_time": "Dinner",
        "ratings": 2.1,
        "picture": "",
        "ratings_count": 45
    },
    {
        "date": "01-22-2022",
        "court": "Ford",
        "food": "Kings Hawaiian Bread Roll",
        "meal_time": "Dinner",
        "ratings": 1.6,
        "picture": "",
        "ratings_count": 71
    },
    {
        "date": "01-22-2022",
        "court": "Ford",
        "food": "Whipped Butter",
        "meal_time": "Dinner",
        "ratings": 1.3,
        "picture": "",
        "ratings_count": 65
    },
    {
        "date": "01-22-2022",
        "court": "Ford",
        "food": "Honey Orange Glazed Carrots",
        "meal_time": "Dinner",
        "ratings": 4.9,
        "picture": "",
        "ratings_count": 39
    },
    {
        "date": "01-22-2022",
        "court": "Ford",
        "food": "Chicken Pesto Pizza",
        "meal_time": "Dinner",
        "ratings": 4.1,
        "picture": "",
        "ratings_count": 4
    },
    {
        "date": "01-22-2022",
        "court": "Ford",
        "food": "Cheese Pizza",
        "meal_time": "Dinner",
        "ratings": 2.2,
        "picture": "",
        "ratings_count": 18
    },
    {
        "date": "01-22-2022",
        "court": "Ford",
        "food": "Sundae Bar",
        "meal_time": "Dinner",
        "ratings": 2.8,
        "picture": "",
        "ratings_count": 79
    },
    {
        "date": "01-22-2022",
        "court": "Ford",
        "food": "Homemade Chocolate Chip Cookie",
        "meal_time": "Dinner",
        "ratings": 3.7,
        "picture": "",
        "ratings_count": 38
    },
    {
        "date": "01-22-2022",
        "court": "Ford",
        "food": "Apple Nut Cake",
        "meal_time": "Dinner",
        "ratings": 3.6,
        "picture": "",
        "ratings_count": 4
    },
    {
        "date": "01-22-2022",
        "court": "Ford",
        "food": "Lemon Meringue Pie",
        "meal_time": "Dinner",
        "ratings": 2.8,
        "picture": "",
        "ratings_count": 66
    },
    {
        "date": "01-22-2022",
        "court": "Ford",
        "food": "Chickpeas and Mushroom Ragout",
        "meal_time": "Dinner",
        "ratings": 4.0,
        "picture": "",
        "ratings_count": 83
    },
    {
        "date": "01-22-2022",
        "court": "Ford",
        "food": "Linguini",
        "meal_time": "Dinner",
        "ratings": 3.0,
        "picture": "",
        "ratings_count": 58
    },
    {
        "date": "01-22-2022",
        "court": "Ford",
        "food": "Whole Green Beans",
        "meal_time": "Dinner",
        "ratings": 1.2,
        "picture": "",
        "ratings_count": 84
    },
    {
        "date": "01-22-2022",
        "court": "Ford",
        "food": "Salad Bar ",
        "meal_time": "Dinner",
        "ratings": 1.6,
        "picture": "",
        "ratings_count": 4
    },
    {
        "date": "01-22-2022",
        "court": "Ford",
        "food": "Vanilla Yogurt",
        "meal_time": "Dinner",
        "ratings": 3.1,
        "picture": "",
        "ratings_count": 86
    },
    {
        "date": "01-22-2022",
        "court": "Ford",
        "food": "Strawberry Yogurt",
        "meal_time": "Dinner",
        "ratings": 1.4,
        "picture": "",
        "ratings_count": 28
    },
    {
        "date": "01-22-2022",
        "court": "Ford",
        "food": "Potato Chips",
        "meal_time": "Dinner",
        "ratings": 4.3,
        "picture": "",
        "ratings_count": 41
    },
    {
        "date": "01-22-2022",
        "court": "Ford",
        "food": "Grapefruit Wedges",
        "meal_time": "Dinner",
        "ratings": 2.9,
        "picture": "",
        "ratings_count": 66
    },
    {
        "date": "01-22-2022",
        "court": "Ford",
        "food": "Mango Chunks",
        "meal_time": "Dinner",
        "ratings": 1.9,
        "picture": "",
        "ratings_count": 70
    },
    {
        "date": "01-22-2022",
        "court": "Ford",
        "food": "Malibu Burger",
        "meal_time": "Dinner",
        "ratings": 2.2,
        "picture": "",
        "ratings_count": 42
    },
    {
        "date": "01-22-2022",
        "court": "Ford",
        "food": "GF White Bread",
        "meal_time": "Dinner",
        "ratings": 4.0,
        "picture": "",
        "ratings_count": 49
    },
    {
        "date": "01-22-2022",
        "court": "Ford",
        "food": "GF Hot Dog Bun",
        "meal_time": "Dinner",
        "ratings": 2.5,
        "picture": "",
        "ratings_count": 41
    },
    {
        "date": "01-22-2022",
        "court": "Ford",
        "food": "GF Hamburger Bun",
        "meal_time": "Dinner",
        "ratings": 2.5,
        "picture": "",
        "ratings_count": 45
    },
    {
        "date": "01-22-2022",
        "court": "Ford",
        "food": "Dark Chocolate Sunflower Butter",
        "meal_time": "Dinner",
        "ratings": 3.2,
        "picture": "",
        "ratings_count": 57
    },
    {
        "date": "01-22-2022",
        "court": "Ford",
        "food": "Smart Balance Margarine",
        "meal_time": "Dinner",
        "ratings": 4.9,
        "picture": "",
        "ratings_count": 4
    },
    {
        "date": "01-22-2022",
        "court": "Ford",
        "food": "Mozz Style Shredded Vegan Cheese",
        "meal_time": "Dinner",
        "ratings": 4.6,
        "picture": "",
        "ratings_count": 63
    },
    {
        "date": "01-22-2022",
        "court": "Ford",
        "food": "GF Pizza Crust",
        "meal_time": "Dinner",
        "ratings": 3.2,
        "picture": "",
        "ratings_count": 19
    },
    {
        "date": "01-22-2022",
        "court": "Ford",
        "food": "Italian Ice",
        "meal_time": "Dinner",
        "ratings": 1.6,
        "picture": "",
        "ratings_count": 24
    },
    {
        "date": "01-22-2022",
        "court": "The Gathering Place",
        "food": "Sushi California Roll",
        "meal_time": "Dinner",
        "ratings": 4.6,
        "picture": "",
        "ratings_count": 40
    },
    {
        "date": "01-22-2022",
        "court": "The Gathering Place",
        "food": "Sushi Crab Philly Roll",
        "meal_time": "Dinner",
        "ratings": 1.8,
        "picture": "",
        "ratings_count": 98
    },
    {
        "date": "01-22-2022",
        "court": "The Gathering Place",
        "food": "Sushi Crunchy Roll",
        "meal_time": "Dinner",
        "ratings": 4.5,
        "picture": "",
        "ratings_count": 3
    },
    {
        "date": "01-22-2022",
        "court": "The Gathering Place",
        "food": "Sushi Firecracker Roll",
        "meal_time": "Dinner",
        "ratings": 2.2,
        "picture": "",
        "ratings_count": 41
    },
    {
        "date": "01-22-2022",
        "court": "The Gathering Place",
        "food": "Sushi Greenhouse Roll",
        "meal_time": "Dinner",
        "ratings": 1.5,
        "picture": "",
        "ratings_count": 47
    },
    {
        "date": "01-22-2022",
        "court": "The Gathering Place",
        "food": "Sushi Philadelphia Roll",
        "meal_time": "Dinner",
        "ratings": 2.6,
        "picture": "",
        "ratings_count": 40
    },
    {
        "date": "01-22-2022",
        "court": "The Gathering Place",
        "food": "Sushi Shrimpin Aint Easy Roll",
        "meal_time": "Dinner",
        "ratings": 3.4,
        "picture": "",
        "ratings_count": 88
    },
    {
        "date": "01-22-2022",
        "court": "The Gathering Place",
        "food": "Sushi Spicy California Roll",
        "meal_time": "Dinner",
        "ratings": 2.7,
        "picture": "",
        "ratings_count": 29
    },
    {
        "date": "01-22-2022",
        "court": "The Gathering Place",
        "food": "Sushi Spicy Crab Rangoon Roll",
        "meal_time": "Dinner",
        "ratings": 1.5,
        "picture": "",
        "ratings_count": 10
    },
    {
        "date": "01-22-2022",
        "court": "The Gathering Place",
        "food": "Sushi Spicy Salmon Roll",
        "meal_time": "Dinner",
        "ratings": 4.2,
        "picture": "",
        "ratings_count": 29
    },
    {
        "date": "01-22-2022",
        "court": "The Gathering Place",
        "food": "Sushi Spicy Tuna Roll",
        "meal_time": "Dinner",
        "ratings": 3.9,
        "picture": "",
        "ratings_count": 92
    },
    {
        "date": "01-22-2022",
        "court": "The Gathering Place",
        "food": "Charashi Bowl",
        "meal_time": "Dinner",
        "ratings": 1.8,
        "picture": "",
        "ratings_count": 34
    },
    {
        "date": "01-22-2022",
        "court": "The Gathering Place",
        "food": "Spicy Crab Salad Bowl",
        "meal_time": "Dinner",
        "ratings": 2.2,
        "picture": "",
        "ratings_count": 1
    },
    {
        "date": "01-22-2022",
        "court": "The Gathering Place",
        "food": "Tropical Spicy Shrimp Bowl",
        "meal_time": "Dinner",
        "ratings": 3.8,
        "picture": "",
        "ratings_count": 61
    },
    {
        "date": "01-22-2022",
        "court": "The Gathering Place",
        "food": "Poke Bowl Hawaiian",
        "meal_time": "Dinner",
        "ratings": 2.0,
        "picture": "",
        "ratings_count": 53
    },
    {
        "date": "01-22-2022",
        "court": "Earhart",
        "food": "Super Beef Hot Dog",
        "meal_time": "Lunch",
        "ratings": 3.2,
        "picture": "",
        "ratings_count": 81
    },
    {
        "date": "01-22-2022",
        "court": "Earhart",
        "food": "Hot Dog Bun",
        "meal_time": "Lunch",
        "ratings": 2.2,
        "picture": "",
        "ratings_count": 61
    },
    {
        "date": "01-22-2022",
        "court": "Earhart",
        "food": "Crinkle Cut Fries",
        "meal_time": "Lunch",
        "ratings": 2.9,
        "picture": "",
        "ratings_count": 39
    },
    {
        "date": "01-22-2022",
        "court": "Earhart",
        "food": "Hamburger",
        "meal_time": "Lunch",
        "ratings": 1.4,
        "picture": "",
        "ratings_count": 48
    },
    {
        "date": "01-22-2022",
        "court": "Earhart",
        "food": "Hamburger Bun",
        "meal_time": "Lunch",
        "ratings": 3.7,
        "picture": "",
        "ratings_count": 97
    },
    {
        "date": "01-22-2022",
        "court": "Earhart",
        "food": "Burger Toppings",
        "meal_time": "Lunch",
        "ratings": 1.8,
        "picture": "",
        "ratings_count": 24
    },
    {
        "date": "01-22-2022",
        "court": "Earhart",
        "food": "Cheeseburger Casserole",
        "meal_time": "Lunch",
        "ratings": 2.6,
        "picture": "",
        "ratings_count": 94
    },
    {
        "date": "01-22-2022",
        "court": "Earhart",
        "food": "Scrambled Eggs with Cheese",
        "meal_time": "Lunch",
        "ratings": 2.8,
        "picture": "",
        "ratings_count": 24
    },
    {
        "date": "01-22-2022",
        "court": "Earhart",
        "food": "Flame Roasted Sweet Potatoes",
        "meal_time": "Lunch",
        "ratings": 2.2,
        "picture": "",
        "ratings_count": 1
    },
    {
        "date": "01-22-2022",
        "court": "Earhart",
        "food": "Peas",
        "meal_time": "Lunch",
        "ratings": 2.3,
        "picture": "",
        "ratings_count": 71
    },
    {
        "date": "01-22-2022",
        "court": "Earhart",
        "food": "Szechuan Beef and Seafood",
        "meal_time": "Lunch",
        "ratings": 3.4,
        "picture": "",
        "ratings_count": 62
    },
    {
        "date": "01-22-2022",
        "court": "Earhart",
        "food": "Long Grain Rice",
        "meal_time": "Lunch",
        "ratings": 1.6,
        "picture": "",
        "ratings_count": 68
    },
    {
        "date": "01-22-2022",
        "court": "Earhart",
        "food": "Fried Rice",
        "meal_time": "Lunch",
        "ratings": 2.7,
        "picture": "",
        "ratings_count": 43
    },
    {
        "date": "01-22-2022",
        "court": "Earhart",
        "food": "Cavatappi Pasta",
        "meal_time": "Lunch",
        "ratings": 1.5,
        "picture": "",
        "ratings_count": 38
    },
    {
        "date": "01-22-2022",
        "court": "Earhart",
        "food": "Marinara Sauce",
        "meal_time": "Lunch",
        "ratings": 2.9,
        "picture": "",
        "ratings_count": 50
    },
    {
        "date": "01-22-2022",
        "court": "Earhart",
        "food": "GF Alfredo Sauce",
        "meal_time": "Lunch",
        "ratings": 4.4,
        "picture": "",
        "ratings_count": 58
    },
    {
        "date": "01-22-2022",
        "court": "Earhart",
        "food": "Garlic Breadstick",
        "meal_time": "Lunch",
        "ratings": 4.7,
        "picture": "",
        "ratings_count": 46
    },
    {
        "date": "01-22-2022",
        "court": "Earhart",
        "food": "Sugar Cookie",
        "meal_time": "Lunch",
        "ratings": 3.2,
        "picture": "",
        "ratings_count": 18
    },
    {
        "date": "01-22-2022",
        "court": "Earhart",
        "food": "Chocolate Pudding",
        "meal_time": "Lunch",
        "ratings": 2.3,
        "picture": "",
        "ratings_count": 40
    },
    {
        "date": "01-22-2022",
        "court": "Earhart",
        "food": "Kings Cheesecake",
        "meal_time": "Lunch",
        "ratings": 4.7,
        "picture": "",
        "ratings_count": 85
    },
    {
        "date": "01-22-2022",
        "court": "Earhart",
        "food": "Fruit Cocktail",
        "meal_time": "Lunch",
        "ratings": 1.6,
        "picture": "",
        "ratings_count": 91
    },
    {
        "date": "01-22-2022",
        "court": "Earhart",
        "food": "Chickpeas and Mushroom Ragout",
        "meal_time": "Lunch",
        "ratings": 5.0,
        "picture": "",
        "ratings_count": 3
    },
    {
        "date": "01-22-2022",
        "court": "Earhart",
        "food": "Roasted Bok Choy",
        "meal_time": "Lunch",
        "ratings": 3.6,
        "picture": "",
        "ratings_count": 61
    },
    {
        "date": "01-22-2022",
        "court": "Earhart",
        "food": "Long Grain Rice",
        "meal_time": "Lunch",
        "ratings": 4.6,
        "picture": "",
        "ratings_count": 90
    },
    {
        "date": "01-22-2022",
        "court": "Earhart",
        "food": "GF Hamburger Bun",
        "meal_time": "Lunch",
        "ratings": 1.6,
        "picture": "",
        "ratings_count": 78
    },
    {
        "date": "01-22-2022",
        "court": "Earhart",
        "food": "GF Hot Dog Bun",
        "meal_time": "Lunch",
        "ratings": 1.4,
        "picture": "",
        "ratings_count": 7
    },
    {
        "date": "01-22-2022",
        "court": "Earhart",
        "food": "GF White Bread",
        "meal_time": "Lunch",
        "ratings": 3.9,
        "picture": "",
        "ratings_count": 73
    },
    {
        "date": "01-22-2022",
        "court": "Earhart",
        "food": "Mozz Style Shredded Vegan Cheese",
        "meal_time": "Lunch",
        "ratings": 3.9,
        "picture": "",
        "ratings_count": 59
    },
    {
        "date": "01-22-2022",
        "court": "Earhart",
        "food": "Smart Balance Margarine",
        "meal_time": "Lunch",
        "ratings": 4.4,
        "picture": "",
        "ratings_count": 81
    },
    {
        "date": "01-22-2022",
        "court": "Earhart",
        "food": "Super Beef Hot Dog",
        "meal_time": "Dinner",
        "ratings": 1.7,
        "picture": "",
        "ratings_count": 98
    },
    {
        "date": "01-22-2022",
        "court": "Earhart",
        "food": "Hot Dog Bun",
        "meal_time": "Dinner",
        "ratings": 1.0,
        "picture": "",
        "ratings_count": 3
    },
    {
        "date": "01-22-2022",
        "court": "Earhart",
        "food": "Crinkle Cut Fries",
        "meal_time": "Dinner",
        "ratings": 1.3,
        "picture": "",
        "ratings_count": 51
    },
    {
        "date": "01-22-2022",
        "court": "Earhart",
        "food": "Hamburger",
        "meal_time": "Dinner",
        "ratings": 2.6,
        "picture": "",
        "ratings_count": 20
    },
    {
        "date": "01-22-2022",
        "court": "Earhart",
        "food": "Hamburger Bun",
        "meal_time": "Dinner",
        "ratings": 3.9,
        "picture": "",
        "ratings_count": 16
    },
    {
        "date": "01-22-2022",
        "court": "Earhart",
        "food": "Burger Toppings",
        "meal_time": "Dinner",
        "ratings": 4.0,
        "picture": "",
        "ratings_count": 81
    },
    {
        "date": "01-22-2022",
        "court": "Earhart",
        "food": "Cavatappi Pasta",
        "meal_time": "Dinner",
        "ratings": 4.1,
        "picture": "",
        "ratings_count": 60
    },
    {
        "date": "01-22-2022",
        "court": "Earhart",
        "food": "Marinara Sauce",
        "meal_time": "Dinner",
        "ratings": 3.4,
        "picture": "",
        "ratings_count": 63
    },
    {
        "date": "01-22-2022",
        "court": "Earhart",
        "food": "GF Alfredo Sauce",
        "meal_time": "Dinner",
        "ratings": 3.3,
        "picture": "",
        "ratings_count": 22
    },
    {
        "date": "01-22-2022",
        "court": "Earhart",
        "food": "Garlic Breadstick",
        "meal_time": "Dinner",
        "ratings": 2.3,
        "picture": "",
        "ratings_count": 33
    },
    {
        "date": "01-22-2022",
        "court": "Earhart",
        "food": "Szechuan Beef and Seafood",
        "meal_time": "Dinner",
        "ratings": 2.3,
        "picture": "",
        "ratings_count": 32
    },
    {
        "date": "01-22-2022",
        "court": "Earhart",
        "food": "Long Grain Rice",
        "meal_time": "Dinner",
        "ratings": 3.7,
        "picture": "",
        "ratings_count": 76
    },
    {
        "date": "01-22-2022",
        "court": "Earhart",
        "food": "Fried Rice",
        "meal_time": "Dinner",
        "ratings": 3.5,
        "picture": "",
        "ratings_count": 63
    },
    {
        "date": "01-22-2022",
        "court": "Earhart",
        "food": "Sugar Cookie",
        "meal_time": "Dinner",
        "ratings": 1.8,
        "picture": "",
        "ratings_count": 42
    },
    {
        "date": "01-22-2022",
        "court": "Earhart",
        "food": "Chocolate Pudding",
        "meal_time": "Dinner",
        "ratings": 3.0,
        "picture": "",
        "ratings_count": 19
    },
    {
        "date": "01-22-2022",
        "court": "Earhart",
        "food": "Kings Cheesecake",
        "meal_time": "Dinner",
        "ratings": 3.4,
        "picture": "",
        "ratings_count": 99
    },
    {
        "date": "01-22-2022",
        "court": "Earhart",
        "food": "Fruit Cocktail",
        "meal_time": "Dinner",
        "ratings": 2.1,
        "picture": "",
        "ratings_count": 23
    },
    {
        "date": "01-22-2022",
        "court": "Earhart",
        "food": "Chickpeas and Mushroom Ragout",
        "meal_time": "Dinner",
        "ratings": 1.9,
        "picture": "",
        "ratings_count": 32
    },
    {
        "date": "01-22-2022",
        "court": "Earhart",
        "food": "Long Grain Rice",
        "meal_time": "Dinner",
        "ratings": 4.9,
        "picture": "",
        "ratings_count": 85
    },
    {
        "date": "01-22-2022",
        "court": "Earhart",
        "food": "Fordhook Lima Beans",
        "meal_time": "Dinner",
        "ratings": 2.8,
        "picture": "",
        "ratings_count": 94
    },
    {
        "date": "01-22-2022",
        "court": "Earhart",
        "food": "GF Hamburger Bun",
        "meal_time": "Dinner",
        "ratings": 1.2,
        "picture": "",
        "ratings_count": 78
    },
    {
        "date": "01-22-2022",
        "court": "Earhart",
        "food": "GF Hot Dog Bun",
        "meal_time": "Dinner",
        "ratings": 4.7,
        "picture": "",
        "ratings_count": 61
    },
    {
        "date": "01-22-2022",
        "court": "Earhart",
        "food": "GF White Bread",
        "meal_time": "Dinner",
        "ratings": 4.9,
        "picture": "",
        "ratings_count": 47
    },
    {
        "date": "01-22-2022",
        "court": "Earhart",
        "food": "Mozz Style Shredded Vegan Cheese",
        "meal_time": "Dinner",
        "ratings": 4.1,
        "picture": "",
        "ratings_count": 20
    },
    {
        "date": "01-22-2022",
        "court": "Earhart",
        "food": "Smart Balance Margarine",
        "meal_time": "Dinner",
        "ratings": 3.4,
        "picture": "",
        "ratings_count": 81
    }
]